{
  "id": "bun",
  "version": "1.0.3",
  "name": "Bun",
  "description": "Minimal, supply-chain-secure dev container with Bun for JS/TypeScript.",
  "publisher": "Bare Dev Container Maintainers",
  "documentationURL": "https://github.com/bare-devcontainer/templates/tree/main/src/bun",
  "licenseURL": "https://github.com/bare-devcontainer/templates/blob/main/LICENSE",
  "options": {
    "imageVariant": {
      "type": "string",
      "description": "Bun version and Debian version",
      "proposals": [
        "1-trixie",
        "1-bookworm"
      ],
      "default": "1-trixie"
    }
  },
  "platforms": [
    "linux"
  ],
  "keywords": [
    "bun",
    "javascript",
    "js",
    "typescript",
    "ts"
  ]
}
